<?xml version="1.0" encoding="utf-8" ?>
<dwsync>
<file name="animated.less" server="www.zqhdesign.com/public_html/heindel_church/" local="131163764307271676" remote="131163941490000000" Dst="2" />
<file name="bordered-pulled.less" server="www.zqhdesign.com/public_html/heindel_church/" local="131163764303136126" remote="131163941510000000" Dst="2" />
<file name="core.less" server="www.zqhdesign.com/public_html/heindel_church/" local="131163764294764997" remote="131163941540000000" Dst="2" />
<file name="fixed-width.less" server="www.zqhdesign.com/public_html/heindel_church/" local="131163764299965718" remote="131163941560000000" Dst="2" />
<file name="font-awesome.less" server="www.zqhdesign.com/public_html/heindel_church/" local="131163764290844475" remote="131163941580000000" Dst="2" />
<file name="icons.less" server="www.zqhdesign.com/public_html/heindel_church/" local="131163764288354133" remote="131163941600000000" Dst="2" />
<file name="larger.less" server="www.zqhdesign.com/public_html/heindel_church/" local="131163764282518363" remote="131163941630000000" Dst="2" />
<file name="list.less" server="www.zqhdesign.com/public_html/heindel_church/" local="131163764298545529" remote="131163941660000000" Dst="2" />
<file name="mixins.less" server="www.zqhdesign.com/public_html/heindel_church/" local="131163764286848948" remote="131163941680000000" Dst="2" />
<file name="path.less" server="www.zqhdesign.com/public_html/heindel_church/" local="131163764296265206" remote="131163941690000000" Dst="2" />
<file name="rotated-flipped.less" server="www.zqhdesign.com/public_html/heindel_church/" local="131163764292314671" remote="131163941700000000" Dst="2" />
<file name="screen-reader.less" server="www.zqhdesign.com/public_html/heindel_church/" local="131163764304096263" remote="131163941730000000" Dst="2" />
<file name="stacked.less" server="www.zqhdesign.com/public_html/heindel_church/" local="131163764283468505" remote="131163941750000000" Dst="2" />
<file name="variables.less" server="www.zqhdesign.com/public_html/heindel_church/" local="131163764279317926" remote="131163941760000000" Dst="2" />
</dwsync>